AUTHORS.txt
CHANGELOG.txt
COPYING.txt
README.txt
TODO.txt
setup.py
bin/shakespeare-admin
bin/shakespeare-profile.py
contrib/size.py
contrib/stats.py
contrib/view_raw.py
etc/shakespeare.conf.new
src/shakespeare/__init__.py
src/shakespeare/cache.py
src/shakespeare/cache_test.py
src/shakespeare/concordance.py
src/shakespeare/concordance_test.py
src/shakespeare/dm.py
src/shakespeare/dm_test.py
src/shakespeare/format.py
src/shakespeare/format_test.py
src/shakespeare/gutenberg.py
src/shakespeare/gutenberg_test.py
src/shakespeare/index.py
src/shakespeare/index_test.py
src/shakespeare/moby.py
src/shakespeare/moby_test.py
src/shakespeare/site_test.py
src/shakespeare/textutils.py
src/shakespeare/textutils_test.py
src/shakespeare/wsgi.py
src/shakespeare/wsgiplain.py
src/shakespeare.egg-info/PKG-INFO
src/shakespeare.egg-info/SOURCES.txt
src/shakespeare.egg-info/dependency_links.txt
src/shakespeare.egg-info/requires.txt
src/shakespeare.egg-info/top_level.txt
src/shakespeare/src/__init__.py
src/shakespeare/src/eb.py
src/shakespeare/src/eb_test.py
src/shakespeare/template/concordance.html
src/shakespeare/template/concordance_by_word.html
src/shakespeare/template/guide.html
src/shakespeare/template/index.html
src/shakespeare/template/layout.html
src/shakespeare/template/view.html
src/shakespeare/template/view_annotate.html
