Metadata-Version: 1.0
Name: shakespeare
Version: 0.4
Summary: A full open set of Shakespeare's works along with anciallary material, a variety of tools and a python api
Home-page: http://www.openshakespeare.org/
Author: Rufus Pollock (Open Knowledge Foundation)
Author-email: rufus.pollock@okfn.org
License: MIT
Download-URL: http://www.openshakespeare.org/code/
Keywords: open shakespeare search view
Platform: UNKNOWN
Classifier: Development Status :: 4 - Beta
Classifier: Environment :: Console
Classifier: Environment :: Web
Classifier: Intended Audience :: Developers
Classifier: License :: OSI Approved :: MIT License
Classifier: Operating System :: OS Independent
Classifier: Programming Language :: Python
Classifier: Topic :: Software Development :: Libraries :: Python Modules
